webviz_petech/__init__.py
webviz_petech-0.0.1.dist-info/METADATA
webviz_petech-0.0.1.dist-info/WHEEL
webviz_petech-0.0.1.dist-info/top_level.txt
webviz_petech-0.0.1.dist-info/RECORD
