Metadata-Version: 2.1
Name: webviz-petech
Version: 0.0.1
Summary: Webviz petech provides webviz plugins related to specialized petech visualizations.
Home-page: https://github.com/Statoil/webviz_petech
Author: Equinor ASA
Author-email: fg_gpl@equinor.com
License: UNKNOWN
Project-URL: Bug Reports, https://github.com/Statoil/webviz_petech/issues
Platform: UNKNOWN
Classifier: Programming Language :: Python :: 2
Classifier: Programming Language :: Python :: 3
Classifier: License :: OSI Approved :: GNU Lesser General Public License v3 or later (LGPLv3+)
Classifier: Operating System :: OS Independent
